{
  "session_summary": {
    "session_id": "dart_fix_1750609931",
    "start_time": "2025-06-22T23:32:11.879916",
    "duration_seconds": 133.95,
    "metrics": {
      "session_id": "dart_fix_1750609931",
      "start_time": 1750609931.879916,
      "end_time": 1750610065.83164,
      "total_attempts": 3,
      "successful_attempts": 1,
      "failed_attempts": 2,
      "commands_executed": 9,
      "fixes_applied": 5,
      "files_modified": 5,
      "initial_error_count": 6,
      "final_error_count": 2,
      "total_duration": 133.9517240524292,
      "success": false
    },
    "total_attempts": 3,
    "total_stages": 24,
    "total_commands": 9,
    "successful_commands": 2,
    "failed_commands": 7,
    "files_modified": 5,
    "latest_attempt": "AttemptLog(attempt_number=3, stage=<RecoveryStage.ERROR_ANALYSIS: 'error_analysis'>, timestamp=1750610036.6828225, duration=26.309818983078003, success=False, error_count_before=2, error_count_after=2, commands_executed=['dart fix --apply', 'dart fix --apply'], fixes_applied=1, files_modified=['lib/screens/login_screen.dart'], error_message=None, context=None)"
  },
  "attempt_logs": [
    {
      "attempt_number": 1,
      "stage": "RecoveryStage.ERROR_ANALYSIS",
      "timestamp": 1750609934.757781,
      "duration": 54.57632279396057,
      "success": false,
      "error_count_before": 6,
      "error_count_after": 7,
      "commands_executed": [
        "dart fix --apply",
        "cat /mnt/c/Users/user/code/walturn/flutter-server/project/lib/screens/login_screen.dart",
        "dart format lib/screens/login_screen.dart"
      ],
      "fixes_applied": 1,
      "files_modified": [
        "lib/screens/login_screen.dart"
      ],
      "error_message": null,
      "context": null
    },
    {
      "attempt_number": 2,
      "stage": "RecoveryStage.ERROR_ANALYSIS",
      "timestamp": 1750609989.3353581,
      "duration": 47.34606051445007,
      "success": true,
      "error_count_before": 7,
      "error_count_after": 2,
      "commands_executed": [
        "flutter pub get",
        "dart fix --apply",
        "flutter pub add http"
      ],
      "fixes_applied": 3,
      "files_modified": [
        "lib/models/user.dart",
        "lib/screens/dashboard_screen.dart",
        "lib/screens/signup_screen.dart"
      ],
      "error_message": null,
      "context": null
    },
    {
      "attempt_number": 3,
      "stage": "RecoveryStage.ERROR_ANALYSIS",
      "timestamp": 1750610036.6828225,
      "duration": 26.309818983078003,
      "success": false,
      "error_count_before": 2,
      "error_count_after": 2,
      "commands_executed": [
        "dart fix --apply",
        "dart fix --apply"
      ],
      "fixes_applied": 1,
      "files_modified": [
        "lib/screens/login_screen.dart"
      ],
      "error_message": null,
      "context": null
    }
  ],
  "stage_logs": [
    {
      "stage": "initialization",
      "timestamp": 1750609931.881961,
      "session_id": "dart_fix_1750609931",
      "attempt_number": null,
      "context": {
        "session_id": "dart_fix_1750609931",
        "initial_error_count": null,
        "start_time": "2025-06-22T23:32:11.879916"
      }
    },
    {
      "stage": "error_capture",
      "timestamp": 1750609931.8831902,
      "session_id": "dart_fix_1750609931",
      "attempt_number": null,
      "context": {}
    },
    {
      "stage": "error_analysis",
      "timestamp": 1750609934.7333577,
      "session_id": "dart_fix_1750609931",
      "attempt_number": null,
      "context": {
        "snapshot": {
          "attempt_number": 0,
          "total_errors": 6,
          "total_warnings": 0,
          "error_categories": {
            "error": 6,
            "type_errors": 6
          },
          "context": "Initial analysis"
        }
      }
    },
    {
      "stage": "initialization",
      "timestamp": 1750609934.73465,
      "session_id": "dart_fix_1750609931",
      "attempt_number": null,
      "context": {
        "session_id": "dart_fix_1750609931",
        "initial_error_count": 6,
        "start_time": "2025-06-22T23:32:11.879916"
      }
    },
    {
      "stage": "command_planning",
      "timestamp": 1750609934.760816,
      "session_id": "dart_fix_1750609931",
      "attempt_number": 1,
      "context": {}
    },
    {
      "stage": "command_execution",
      "timestamp": 1750609934.7608447,
      "session_id": "dart_fix_1750609931",
      "attempt_number": 1,
      "context": {}
    },
    {
      "stage": "fix_generation",
      "timestamp": 1750609936.6188138,
      "session_id": "dart_fix_1750609931",
      "attempt_number": 1,
      "context": {}
    },
    {
      "stage": "fix_application",
      "timestamp": 1750609988.0735445,
      "session_id": "dart_fix_1750609931",
      "attempt_number": 1,
      "context": {}
    },
    {
      "stage": "error_analysis",
      "timestamp": 1750609989.330179,
      "session_id": "dart_fix_1750609931",
      "attempt_number": 1,
      "context": {
        "snapshot": {
          "attempt_number": 1,
          "total_errors": 7,
          "total_warnings": 0,
          "error_categories": {
            "error": 7,
            "other_errors": 5,
            "undefined_symbols": 1,
            "type_errors": 1,
            "info": 2
          },
          "context": "After attempt 1"
        }
      }
    },
    {
      "stage": "progress_analysis",
      "timestamp": 1750609989.331489,
      "session_id": "dart_fix_1750609931",
      "attempt_number": 1,
      "context": {
        "diff": {
          "from_attempt": 0,
          "to_attempt": 1,
          "progress_score": 0.0,
          "regression_score": 0.5,
          "summary": {
            "new": 1,
            "modified": 1,
            "errors_modified": 1
          },
          "changes_count": 2
        }
      }
    },
    {
      "stage": "command_planning",
      "timestamp": 1750609989.337871,
      "session_id": "dart_fix_1750609931",
      "attempt_number": 2,
      "context": {}
    },
    {
      "stage": "command_execution",
      "timestamp": 1750609989.3379114,
      "session_id": "dart_fix_1750609931",
      "attempt_number": 2,
      "context": {}
    },
    {
      "stage": "fix_generation",
      "timestamp": 1750609997.1123667,
      "session_id": "dart_fix_1750609931",
      "attempt_number": 2,
      "context": {}
    },
    {
      "stage": "fix_application",
      "timestamp": 1750610035.1317701,
      "session_id": "dart_fix_1750609931",
      "attempt_number": 2,
      "context": {}
    },
    {
      "stage": "error_analysis",
      "timestamp": 1750610036.6769927,
      "session_id": "dart_fix_1750609931",
      "attempt_number": 2,
      "context": {
        "snapshot": {
          "attempt_number": 2,
          "total_errors": 2,
          "total_warnings": 3,
          "error_categories": {
            "error": 2,
            "other_errors": 1,
            "type_errors": 1,
            "warning": 3
          },
          "context": "After attempt 2"
        }
      }
    },
    {
      "stage": "progress_analysis",
      "timestamp": 1750610036.6785538,
      "session_id": "dart_fix_1750609931",
      "attempt_number": 2,
      "context": {
        "diff": {
          "from_attempt": 1,
          "to_attempt": 2,
          "progress_score": 0.7142857142857144,
          "regression_score": 0.3333333333333333,
          "summary": {
            "fixed": 1,
            "new": 1,
            "warnings_new": 1,
            "modified": 1,
            "errors_modified": 1
          },
          "changes_count": 3
        }
      }
    },
    {
      "stage": "command_planning",
      "timestamp": 1750610036.6853426,
      "session_id": "dart_fix_1750609931",
      "attempt_number": 3,
      "context": {}
    },
    {
      "stage": "command_execution",
      "timestamp": 1750610036.6853654,
      "session_id": "dart_fix_1750609931",
      "attempt_number": 3,
      "context": {}
    },
    {
      "stage": "fix_generation",
      "timestamp": 1750610044.7118392,
      "session_id": "dart_fix_1750609931",
      "attempt_number": 3,
      "context": {}
    },
    {
      "stage": "fix_application",
      "timestamp": 1750610061.7104466,
      "session_id": "dart_fix_1750609931",
      "attempt_number": 3,
      "context": {}
    },
    {
      "stage": "error_analysis",
      "timestamp": 1750610062.9884157,
      "session_id": "dart_fix_1750609931",
      "attempt_number": 3,
      "context": {
        "snapshot": {
          "attempt_number": 3,
          "total_errors": 2,
          "total_warnings": 0,
          "error_categories": {
            "error": 2,
            "other_errors": 2,
            "info": 4
          },
          "context": "After attempt 3"
        }
      }
    },
    {
      "stage": "progress_analysis",
      "timestamp": 1750610062.98982,
      "session_id": "dart_fix_1750609931",
      "attempt_number": 3,
      "context": {
        "diff": {
          "from_attempt": 2,
          "to_attempt": 3,
          "progress_score": 0.2,
          "regression_score": 0.3333333333333333,
          "summary": {
            "fixed": 1,
            "warnings_fixed": 1,
            "new": 1,
            "modified": 1,
            "errors_modified": 1
          },
          "changes_count": 3
        }
      }
    },
    {
      "stage": "validation",
      "timestamp": 1750610062.9943259,
      "session_id": "dart_fix_1750609931",
      "attempt_number": null,
      "context": {}
    },
    {
      "stage": "failure",
      "timestamp": 1750610065.8316562,
      "session_id": "dart_fix_1750609931",
      "attempt_number": null,
      "context": {
        "session_id": "dart_fix_1750609931",
        "success": false,
        "final_error_count": 2,
        "total_duration": 133.9517240524292,
        "error_message": null,
        "metrics": {
          "session_id": "dart_fix_1750609931",
          "start_time": 1750609931.879916,
          "end_time": 1750610065.83164,
          "total_attempts": 3,
          "successful_attempts": 1,
          "failed_attempts": 2,
          "commands_executed": 9,
          "fixes_applied": 5,
          "files_modified": 5,
          "initial_error_count": 6,
          "final_error_count": 2,
          "total_duration": 133.9517240524292,
          "success": false
        }
      }
    }
  ],
  "command_logs": [
    {
      "timestamp": 1750609933.4020054,
      "session_id": "dart_fix_1750609931",
      "attempt_number": null,
      "command": "flutter pub get",
      "args": [
        "get"
      ],
      "success": false,
      "exit_code": -1,
      "execution_time": 1.5042524337768555,
      "timeout": false,
      "error_message": "Command execution failed: <LogCategory.SHELL_CMD: 'shell_command'>",
      "context": "Initial pub get",
      "stdout_length": 0,
      "stderr_length": 0
    },
    {
      "timestamp": 1750609936.617407,
      "session_id": "dart_fix_1750609931",
      "attempt_number": 1,
      "command": "dart fix --apply",
      "args": [
        "--apply"
      ],
      "success": false,
      "exit_code": -1,
      "execution_time": 1.8520147800445557,
      "timeout": false,
      "error_message": "Command execution failed: <LogCategory.SHELL_CMD: 'shell_command'>",
      "context": "Automatic dart fix",
      "stdout_length": 0,
      "stderr_length": 0
    },
    {
      "timestamp": 1750609988.0687206,
      "session_id": "dart_fix_1750609931",
      "attempt_number": 1,
      "command": "cat /mnt/c/Users/user/code/walturn/flutter-server/project/lib/screens/login_screen.dart",
      "args": [],
      "success": true,
      "exit_code": 0,
      "execution_time": 0.0050008296966552734,
      "timeout": false,
      "error_message": null,
      "context": "AI-suggested shell command",
      "stdout_length": 13015,
      "stderr_length": 0
    },
    {
      "timestamp": 1750609988.0705738,
      "session_id": "dart_fix_1750609931",
      "attempt_number": 1,
      "command": "dart format lib/screens/login_screen.dart",
      "args": [],
      "success": false,
      "exit_code": 65,
      "execution_time": 0.4175071716308594,
      "timeout": false,
      "error_message": "Could not format because the source could not be parsed:\n\nline 173, column 46 of lib/screens/login_screen.dart: Expected an identifier.\n    \u2577\n173 \u2502                           if (!_isLoginMode) ..[\n    \u2502                                              ^^\n    \u2575\nline 192, column 30 of lib/screens/login_screen.dart: Expected to find ']'.\n    \u2577\n192 \u2502                             ),\n    \u2502                              ^\n    \u2575\nline 255, column 54 of lib/screens/login_screen.dart: Expected an identifier.\n    \u2577\n255 \u2502                           if (_errorMessage != null) ..[\n    \u2502                                                      ^^\n    \u2575\nline 275, column 30 of lib/screens/login_screen.dart: Expected to find ']'.\n    \u2577\n275 \u2502                             ),\n    \u2502                              ^\n    \u2575\nline 314, column 35 of lib/screens/login_screen.dart: Expected an identifier.\n    \u2577\n314 \u2502                 if (_isLoginMode) ..[\n    \u2502                                   ^^\n    \u2575\nline 324, column 20 of lib/screens/login_screen.dart: Expected to find ']'.\n    \u2577\n324 \u2502                   ),\n    \u2502                    ^\n    \u2575\n",
      "context": "AI-suggested shell command",
      "stdout_length": 36,
      "stderr_length": 1115
    },
    {
      "timestamp": 1750609990.820715,
      "session_id": "dart_fix_1750609931",
      "attempt_number": 2,
      "command": "flutter pub get",
      "args": [
        "get"
      ],
      "success": false,
      "exit_code": -1,
      "execution_time": 1.4775400161743164,
      "timeout": false,
      "error_message": "Command execution failed: <LogCategory.SHELL_CMD: 'shell_command'>",
      "context": "Suggested command for error fixing",
      "stdout_length": 0,
      "stderr_length": 0
    },
    {
      "timestamp": 1750609997.111006,
      "session_id": "dart_fix_1750609931",
      "attempt_number": 2,
      "command": "dart fix --apply",
      "args": [
        "--apply"
      ],
      "success": false,
      "exit_code": -1,
      "execution_time": 4.581623077392578,
      "timeout": false,
      "error_message": "Command execution failed: <LogCategory.SHELL_CMD: 'shell_command'>",
      "context": "Automatic dart fix",
      "stdout_length": 0,
      "stderr_length": 0
    },
    {
      "timestamp": 1750610035.1285787,
      "session_id": "dart_fix_1750609931",
      "attempt_number": 2,
      "command": "flutter pub add http",
      "args": [],
      "success": true,
      "exit_code": 0,
      "execution_time": 1.612987756729126,
      "timeout": false,
      "error_message": null,
      "context": "AI-suggested shell command",
      "stdout_length": 747,
      "stderr_length": 0
    },
    {
      "timestamp": 1750610041.584794,
      "session_id": "dart_fix_1750609931",
      "attempt_number": 3,
      "command": "dart fix --apply",
      "args": [
        "--apply"
      ],
      "success": false,
      "exit_code": -1,
      "execution_time": 4.894465208053589,
      "timeout": false,
      "error_message": "Command execution failed: <LogCategory.SHELL_CMD: 'shell_command'>",
      "context": "Suggested command for error fixing",
      "stdout_length": 0,
      "stderr_length": 0
    },
    {
      "timestamp": 1750610044.7104456,
      "session_id": "dart_fix_1750609931",
      "attempt_number": 3,
      "command": "dart fix --apply",
      "args": [
        "--apply"
      ],
      "success": false,
      "exit_code": -1,
      "execution_time": 2.118800401687622,
      "timeout": false,
      "error_message": "Command execution failed: <LogCategory.SHELL_CMD: 'shell_command'>",
      "context": "Automatic dart fix",
      "stdout_length": 0,
      "stderr_length": 0
    }
  ],
  "export_timestamp": "2025-06-22T23:34:25.832952"
}